<wgo>
	<site>
		<item>
			<image>pics/1.jpg</image>
			<lyric space="false"><![CDATA[What's Going on . . . ]]></lyric>		
		</item>
		
		<item>
			<image>pics/2.jpg</image>
			<lyric space="false"><![CDATA[Mother, mother<br>There's too many of you crying]]></lyric>		
		</item>
		<item>
			<image>pics/3.jpg</image>
			<lyric space="true"><![CDATA[Brother, brother, brother]]></lyric>		
		</item>
		<item>
			<image>pics/4.jpg</image>
			<lyric space="false"><![CDATA[There's far too many of you dying<br>You know we've got to find a way]]></lyric>		
		</item>
		<item>
			<image>pics/5.jpg</image>
			<lyric space="false"><![CDATA[To bring some lovin' here today]]></lyric>		
		</item>
		<item>
			<image>pics/6.jpg</image>
			<lyric space="true"><![CDATA[Father, father<br>We don't need to escalate<br>You see, war is not the answer<br>For only love can conquer hate<br>You know we've got to find a way]]></lyric>		
		</item>
		<item>
			<image>pics/7.jpg</image>
			<lyric space="false"><![CDATA[To bring some lovin' here today]]></lyric>		
		</item>
		<item>
			<image>pics/8.jpg</image>
			<lyric space="false"><![CDATA[Picket lines and picket signs<br>Don't punish me with brutality<br>Talk to me, so you can see<br>What's going on...]]></lyric>		
		</item>
		<item>
			<image>pics/9.jpg</image>
			<lyric space="false"><![CDATA[Ya, what's going on<br>Ah, what's going on]]></lyric>		
		</item>
		<item>
			<image>pics/10.jpg</image>
			<lyric space="true"><![CDATA[In the mean time<br>Right on, baby<br>Right on, baby]]></lyric>		
		</item>
		<item>
			<image>pics/11.jpg</image>
			<lyric space="false"><![CDATA[Father, father<br>everybody thinks we're wrong<br>Oh, but who are they to judge us<br>Simply because our hair is long]]></lyric>		
		</item>
		<item>
			<image>pics/12.jpg</image>
			<lyric space="false"><![CDATA[Oh, you know we've got to find a way<br>To bring some understanding here today]]></lyric>		
		</item>
		<item>
			<image>pics/13.jpg</image>
			<lyric space="false"><![CDATA[Picket lines and picket signs<br>Don't punish me with brutality<br>Talk to me<br>So you can see]]></lyric>		
		</item>
		<item>
			<image>pics/14.jpg</image>
			<lyric space="false"><![CDATA[What's going on]]></lyric>		
		</item>
		<item>
			<image>pics/15.jpg</image>
			<lyric space="false"><![CDATA[Ya, what's going on<br>Tell me what's going on]]></lyric>		
		</item>	
	
	
	</site>




</wgo>